KMMTR/KMM.py
KMMTR/KMMTR.py
KMMTR/__init__.py
KMMTR-1.1.3.dist-info/METADATA
KMMTR-1.1.3.dist-info/WHEEL
KMMTR-1.1.3.dist-info/top_level.txt
KMMTR-1.1.3.dist-info/RECORD
