Metadata-Version: 2.1
Name: KMMTR
Version: 1.1.3
Summary: a transfer learning regression model based on Kernel Mean Matching (KMM) algorithm
Home-page: https://github.com/Bin-Cao/KMMTransferRegressor
Author: CaoBin
Author-email: bcao@shu.edu.com
Maintainer: CaoBin
Maintainer-email: binjacobcao@gmail.com
License: MIT License
Classifier: Development Status :: 3 - Alpha
Classifier: Intended Audience :: Developers
Classifier: Topic :: Software Development :: Build Tools
Classifier: License :: OSI Approved :: MIT License
Classifier: Programming Language :: Python :: 3
Requires-Python: >=3.7
Requires-Dist: scikit-learn
Requires-Dist: pandas
Requires-Dist: numpy
Requires-Dist: cvxopt
